{
  "summary": {
    "audit_events_total": 17122,
    "directional_decisions_total": 12868,
    "unique_markets": 146,
    "decisions_with_trade_result": 366,
    "decisions_without_trade_result": 12502,
    "traded_markets": 47,
    "winning_trades": 22,
    "losing_trades": 25,
    "total_pnl": -17.4033,
    "avg_pnl": -0.37028297872340427,
    "win_rate": 0.46808510638297873
  },
  "decisions_per_market_distribution": {
    "1": 6,
    "2": 1,
    "5": 1,
    "6": 2,
    "7": 1,
    "9": 2,
    "12": 1,
    "16": 1,
    "20": 1,
    "22": 1,
    "26": 1,
    "42": 1,
    "45": 3,
    "47": 3,
    "49": 3,
    "50": 1,
    "51": 1,
    "52": 1,
    "53": 3,
    "54": 6,
    "55": 2,
    "57": 3,
    "58": 5,
    "59": 2,
    "60": 2,
    "61": 1,
    "62": 3,
    "63": 2,
    "64": 12,
    "65": 1,
    "66": 1,
    "67": 2,
    "68": 1,
    "69": 1,
    "70": 1,
    "71": 2,
    "72": 1,
    "73": 1,
    "74": 3,
    "78": 1,
    "79": 4,
    "80": 2,
    "81": 3,
    "83": 3,
    "84": 3,
    "85": 2,
    "89": 1,
    "96": 1,
    "100": 1,
    "108": 1,
    "110": 1,
    "112": 1,
    "120": 2,
    "126": 1,
    "130": 1,
    "145": 1,
    "153": 2,
    "163": 1,
    "164": 1,
    "172": 1,
    "176": 2,
    "184": 3,
    "185": 1,
    "187": 1,
    "188": 2,
    "189": 2,
    "190": 2,
    "195": 1,
    "196": 1,
    "201": 1,
    "202": 1,
    "204": 1,
    "209": 1,
    "211": 1,
    "213": 1,
    "219": 1,
    "222": 1,
    "223": 1,
    "224": 1,
    "232": 1
  },
  "factors": {
    "D1": {
      "name": "Price vs Price-to-Beat",
      "configured_weight": null,
      "active_count": 12462,
      "neutral_count": 256,
      "missing_count": 150,
      "active_rate": 0.9684488654025489,
      "neutral_rate": 0.019894311470313956,
      "missing_rate": 0.011656823127137084,
      "avg_abs_contribution": 1.835124962203155,
      "avg_signed_contribution_up": 0.76635781039776,
      "avg_signed_contribution_down": -1.068767151805395,
      "win_rate_when_active": 0.3888888888888889,
      "avg_pnl_when_active": -0.6305499999999999,
      "win_rate_when_neutral": null,
      "avg_pnl_when_neutral": null
    },
    "D2": {
      "name": "Time-adjusted ATR Distance",
      "configured_weight": null,
      "active_count": 12462,
      "neutral_count": 256,
      "missing_count": 150,
      "active_rate": 0.9684488654025489,
      "neutral_rate": 0.019894311470313956,
      "missing_rate": 0.011656823127137084,
      "avg_abs_contribution": 1.3661414465400505,
      "avg_signed_contribution_up": 0.5742197777636047,
      "avg_signed_contribution_down": -0.791921668776446,
      "win_rate_when_active": 0.3888888888888889,
      "avg_pnl_when_active": -0.6305499999999999,
      "win_rate_when_neutral": null,
      "avg_pnl_when_neutral": null
    },
    "D3": {
      "name": "Multi-horizon Return Slope",
      "configured_weight": null,
      "active_count": 12125,
      "neutral_count": 593,
      "missing_count": 150,
      "active_rate": 0.942259869443581,
      "neutral_rate": 0.04608330742928194,
      "missing_rate": 0.011656823127137084,
      "avg_abs_contribution": 0.6624885968731906,
      "avg_signed_contribution_up": 0.27074387825781243,
      "avg_signed_contribution_down": -0.39174471861537824,
      "win_rate_when_active": 0.35294117647058826,
      "avg_pnl_when_active": -0.7823470588235294,
      "win_rate_when_neutral": 1.0,
      "avg_pnl_when_neutral": 1.9500000000000002
    },
    "D4": {
      "name": "Window VWAP / TWAP Position",
      "configured_weight": null,
      "active_count": 10029,
      "neutral_count": 2689,
      "missing_count": 150,
      "active_rate": 0.7793751942803855,
      "neutral_rate": 0.20896798259247745,
      "missing_rate": 0.011656823127137084,
      "avg_abs_contribution": 0.7088504039332497,
      "avg_signed_contribution_up": 0.2726921779220442,
      "avg_signed_contribution_down": -0.43615822601120546,
      "win_rate_when_active": 0.4117647058823529,
      "avg_pnl_when_active": -0.5735235294117648,
      "win_rate_when_neutral": 0.0,
      "avg_pnl_when_neutral": -1.6
    },
    "D5": {
      "name": "Path Structure",
      "configured_weight": null,
      "active_count": 8503,
      "neutral_count": 4215,
      "missing_count": 150,
      "active_rate": 0.6607864470003109,
      "neutral_rate": 0.3275567298725521,
      "missing_rate": 0.011656823127137084,
      "avg_abs_contribution": 0.45129147664727165,
      "avg_signed_contribution_up": 0.1934561251769146,
      "avg_signed_contribution_down": -0.25783535147035697,
      "win_rate_when_active": 0.5,
      "avg_pnl_when_active": -0.1624875,
      "win_rate_when_neutral": 0.3,
      "avg_pnl_when_neutral": -1.005
    },
    "D6": {
      "name": "Mean Reversion Risk",
      "configured_weight": null,
      "active_count": 6271,
      "neutral_count": 6447,
      "missing_count": 150,
      "active_rate": 0.48733291886851104,
      "neutral_rate": 0.5010102580043518,
      "missing_rate": 0.011656823127137084,
      "avg_abs_contribution": 0.5177347067148922,
      "avg_signed_contribution_up": 0.18691618178958955,
      "avg_signed_contribution_down": -0.33081852492530267,
      "win_rate_when_active": 0.35294117647058826,
      "avg_pnl_when_active": -0.7705823529411765,
      "win_rate_when_neutral": 1.0,
      "avg_pnl_when_neutral": 1.75
    },
    "D7": {
      "name": "Multi-exchange Consensus",
      "configured_weight": null,
      "active_count": 5835,
      "neutral_count": 6883,
      "missing_count": 150,
      "active_rate": 0.4534504196456326,
      "neutral_rate": 0.5348927572272303,
      "missing_rate": 0.011656823127137084,
      "avg_abs_contribution": 0.2752791319389842,
      "avg_signed_contribution_up": 0.10298789117785817,
      "avg_signed_contribution_down": -0.17229124076112598,
      "win_rate_when_active": 0.3333333333333333,
      "avg_pnl_when_active": -0.89666,
      "win_rate_when_neutral": 0.6666666666666666,
      "avg_pnl_when_neutral": 0.6999999999999998
    },
    "D8": {
      "name": "Chainlink Lag / Update Risk",
      "configured_weight": null,
      "active_count": 7077,
      "neutral_count": 5641,
      "missing_count": 150,
      "active_rate": 0.5499689151383277,
      "neutral_rate": 0.4383742617345353,
      "missing_rate": 0.011656823127137084,
      "avg_abs_contribution": 0.6148832363579179,
      "avg_signed_contribution_up": 0.4555366409812864,
      "avg_signed_contribution_down": -0.15934659537663154,
      "win_rate_when_active": 0.3888888888888889,
      "avg_pnl_when_active": -0.6305499999999999,
      "win_rate_when_neutral": null,
      "avg_pnl_when_neutral": null
    }
  },
  "d6": {
    "d6_high_count": 1863,
    "d6_medium_count": 4328,
    "d6_low_count": 6527,
    "win_rate_by_d6_risk_level": {
      "low": 0.35294117647058826,
      "medium": 1.0,
      "unknown": 0.5172413793103449
    },
    "avg_pnl_by_d6_risk_level": {
      "low": -0.7705823529411765,
      "medium": 1.75,
      "unknown": -0.20873793103448277
    },
    "blocked_by_mean_reversion_count": 1863,
    "mean_reversion_risk_high_count": 1863,
    "distance_shrinking_true_count": 6696,
    "win_rate_when_distance_shrinking_true": 0.4,
    "avg_pnl_when_distance_shrinking_true": -0.71998
  },
  "d7": {
    "d7_active_count": 5835,
    "d7_neutral_count": 6883,
    "d7_insufficient_data_count": 0,
    "d7_neutral_rate": 0.5348927572272303,
    "d7_insufficient_data_rate": 0.0,
    "win_rate_when_d7_active": 0.3333333333333333,
    "avg_pnl_when_d7_active": -0.89666,
    "win_rate_when_d7_neutral": 0.6666666666666666,
    "avg_pnl_when_d7_neutral": 0.6999999999999998
  },
  "d1_d2_correlation": {
    "sample_count": 12718,
    "pearson": 0.9812830286956792,
    "warning": true
  },
  "d1_d2_directional_correlation": {
    "all_decisions": {
      "sample_count": 12718,
      "pearson": 0.9812830286956792,
      "warning": true
    },
    "up_decisions": {
      "sample_count": 5313,
      "pearson": 0.5530695959995219,
      "warning": false
    },
    "down_decisions": {
      "sample_count": 7400,
      "pearson": 0.6793790070638026,
      "warning": false
    },
    "traded_decisions": {
      "sample_count": 18,
      "pearson": 0.6484900898279745,
      "warning": false
    },
    "losing_trades": {
      "sample_count": 11,
      "pearson": null,
      "warning": false
    },
    "winning_trades": {
      "sample_count": 7,
      "pearson": 0.762427369067258,
      "warning": true
    }
  },
  "entry_price_buckets": {
    "<0.30": {
      "trades": 3,
      "wins": 1,
      "losses": 2,
      "win_rate": 0.3333333333333333,
      "total_pnl": 1.4,
      "avg_pnl": 0.4666666666666666,
      "avg_entry_price": 0.24
    },
    "0.30-0.40": {
      "trades": 3,
      "wins": 0,
      "losses": 3,
      "win_rate": 0.0,
      "total_pnl": -5.25,
      "avg_pnl": -1.75,
      "avg_entry_price": 0.35000000000000003
    },
    "0.40-0.50": {
      "trades": 7,
      "wins": 0,
      "losses": 7,
      "win_rate": 0.0,
      "total_pnl": -16.6969,
      "avg_pnl": -2.3852714285714285,
      "avg_entry_price": 0.4770542857142857
    },
    "0.50-0.60": {
      "trades": 16,
      "wins": 11,
      "losses": 5,
      "win_rate": 0.6875,
      "total_pnl": 10.1465,
      "avg_pnl": 0.63415625,
      "avg_entry_price": 0.5606247495592243
    },
    "0.60-0.65": {
      "trades": 18,
      "wins": 10,
      "losses": 8,
      "win_rate": 0.5555555555555556,
      "total_pnl": -7.0028999999999995,
      "avg_pnl": -0.38904999999999995,
      "avg_entry_price": 0.6333331444068626
    },
    ">0.65": {
      "trades": 0,
      "wins": 0,
      "losses": 0,
      "win_rate": null,
      "total_pnl": null,
      "avg_pnl": null,
      "avg_entry_price": null
    },
    "unknown": {
      "trades": 0,
      "wins": 0,
      "losses": 0,
      "win_rate": null,
      "total_pnl": null,
      "avg_pnl": null,
      "avg_entry_price": null
    }
  },
  "direction_breakdown": {
    "UP": {
      "trades": 46,
      "wins": 21,
      "losses": 25,
      "win_rate": 0.45652173913043476,
      "total_pnl": -19.8033,
      "avg_pnl": -0.43050652173913045,
      "avg_entry_price": 0.54259505635372
    },
    "DOWN": {
      "trades": 1,
      "wins": 1,
      "losses": 0,
      "win_rate": 1.0,
      "total_pnl": 2.4,
      "avg_pnl": 2.4,
      "avg_entry_price": 0.52
    }
  },
  "entry_price_bucket_by_direction": {
    "<0.30": {
      "UP": {
        "trades": 3,
        "wins": 1,
        "losses": 2,
        "win_rate": 0.3333333333333333,
        "total_pnl": 1.4,
        "avg_pnl": 0.4666666666666666,
        "avg_entry_price": 0.24
      },
      "DOWN": {
        "trades": 0,
        "wins": 0,
        "losses": 0,
        "win_rate": null,
        "total_pnl": null,
        "avg_pnl": null,
        "avg_entry_price": null
      }
    },
    "0.30-0.40": {
      "UP": {
        "trades": 3,
        "wins": 0,
        "losses": 3,
        "win_rate": 0.0,
        "total_pnl": -5.25,
        "avg_pnl": -1.75,
        "avg_entry_price": 0.35000000000000003
      },
      "DOWN": {
        "trades": 0,
        "wins": 0,
        "losses": 0,
        "win_rate": null,
        "total_pnl": null,
        "avg_pnl": null,
        "avg_entry_price": null
      }
    },
    "0.40-0.50": {
      "UP": {
        "trades": 7,
        "wins": 0,
        "losses": 7,
        "win_rate": 0.0,
        "total_pnl": -16.6969,
        "avg_pnl": -2.3852714285714285,
        "avg_entry_price": 0.4770542857142857
      },
      "DOWN": {
        "trades": 0,
        "wins": 0,
        "losses": 0,
        "win_rate": null,
        "total_pnl": null,
        "avg_pnl": null,
        "avg_entry_price": null
      }
    },
    "0.50-0.60": {
      "UP": {
        "trades": 15,
        "wins": 10,
        "losses": 5,
        "win_rate": 0.6666666666666666,
        "total_pnl": 7.746499999999999,
        "avg_pnl": 0.5164333333333333,
        "avg_entry_price": 0.5633330661965059
      },
      "DOWN": {
        "trades": 1,
        "wins": 1,
        "losses": 0,
        "win_rate": 1.0,
        "total_pnl": 2.4,
        "avg_pnl": 2.4,
        "avg_entry_price": 0.52
      }
    },
    "0.60-0.65": {
      "UP": {
        "trades": 18,
        "wins": 10,
        "losses": 8,
        "win_rate": 0.5555555555555556,
        "total_pnl": -7.0028999999999995,
        "avg_pnl": -0.38904999999999995,
        "avg_entry_price": 0.6333331444068626
      },
      "DOWN": {
        "trades": 0,
        "wins": 0,
        "losses": 0,
        "win_rate": null,
        "total_pnl": null,
        "avg_pnl": null,
        "avg_entry_price": null
      }
    },
    ">0.65": {
      "UP": {
        "trades": 0,
        "wins": 0,
        "losses": 0,
        "win_rate": null,
        "total_pnl": null,
        "avg_pnl": null,
        "avg_entry_price": null
      },
      "DOWN": {
        "trades": 0,
        "wins": 0,
        "losses": 0,
        "win_rate": null,
        "total_pnl": null,
        "avg_pnl": null,
        "avg_entry_price": null
      }
    },
    "unknown": {
      "UP": {
        "trades": 0,
        "wins": 0,
        "losses": 0,
        "win_rate": null,
        "total_pnl": null,
        "avg_pnl": null,
        "avg_entry_price": null
      },
      "DOWN": {
        "trades": 0,
        "wins": 0,
        "losses": 0,
        "win_rate": null,
        "total_pnl": null,
        "avg_pnl": null,
        "avg_entry_price": null
      }
    }
  },
  "d7_direction_breakdown": {
    "active": {
      "UP": {
        "trades": 15,
        "wins": 5,
        "losses": 10,
        "win_rate": 0.3333333333333333,
        "total_pnl": -13.4499,
        "avg_pnl": -0.89666,
        "avg_entry_price": 0.5126653333333333
      },
      "DOWN": {
        "trades": 0,
        "wins": 0,
        "losses": 0,
        "win_rate": null,
        "total_pnl": null,
        "avg_pnl": null,
        "avg_entry_price": null
      }
    },
    "neutral": {
      "UP": {
        "trades": 3,
        "wins": 2,
        "losses": 1,
        "win_rate": 0.6666666666666666,
        "total_pnl": 2.0999999999999996,
        "avg_pnl": 0.6999999999999998,
        "avg_entry_price": 0.5266666666666667
      },
      "DOWN": {
        "trades": 0,
        "wins": 0,
        "losses": 0,
        "win_rate": null,
        "total_pnl": null,
        "avg_pnl": null,
        "avg_entry_price": null
      }
    },
    "missing": {
      "UP": {
        "trades": 28,
        "wins": 14,
        "losses": 14,
        "win_rate": 0.5,
        "total_pnl": -8.4534,
        "avg_pnl": -0.3019071428571429,
        "avg_entry_price": 0.5603354497239684
      },
      "DOWN": {
        "trades": 1,
        "wins": 1,
        "losses": 0,
        "win_rate": 1.0,
        "total_pnl": 2.4,
        "avg_pnl": 2.4,
        "avg_entry_price": 0.52
      }
    }
  },
  "d6_distance_shrinking_breakdown": {
    "true": {
      "UP": {
        "low": {
          "trades": 4,
          "wins": 1,
          "losses": 3,
          "win_rate": 0.25,
          "total_pnl": -5.3499,
          "avg_pnl": -1.337475,
          "avg_entry_price": 0.517495
        },
        "medium": {
          "trades": 1,
          "wins": 1,
          "losses": 0,
          "win_rate": 1.0,
          "total_pnl": 1.75,
          "avg_pnl": 1.75,
          "avg_entry_price": 0.65
        },
        "high": {
          "trades": 0,
          "wins": 0,
          "losses": 0,
          "win_rate": null,
          "total_pnl": null,
          "avg_pnl": null,
          "avg_entry_price": null
        },
        "unknown": {
          "trades": 0,
          "wins": 0,
          "losses": 0,
          "win_rate": null,
          "total_pnl": null,
          "avg_pnl": null,
          "avg_entry_price": null
        }
      },
      "DOWN": {
        "low": {
          "trades": 0,
          "wins": 0,
          "losses": 0,
          "win_rate": null,
          "total_pnl": null,
          "avg_pnl": null,
          "avg_entry_price": null
        },
        "medium": {
          "trades": 0,
          "wins": 0,
          "losses": 0,
          "win_rate": null,
          "total_pnl": null,
          "avg_pnl": null,
          "avg_entry_price": null
        },
        "high": {
          "trades": 0,
          "wins": 0,
          "losses": 0,
          "win_rate": null,
          "total_pnl": null,
          "avg_pnl": null,
          "avg_entry_price": null
        },
        "unknown": {
          "trades": 0,
          "wins": 0,
          "losses": 0,
          "win_rate": null,
          "total_pnl": null,
          "avg_pnl": null,
          "avg_entry_price": null
        }
      }
    },
    "false": {
      "UP": {
        "low": {
          "trades": 13,
          "wins": 5,
          "losses": 8,
          "win_rate": 0.38461538461538464,
          "total_pnl": -7.75,
          "avg_pnl": -0.5961538461538461,
          "avg_entry_price": 0.5038461538461538
        },
        "medium": {
          "trades": 0,
          "wins": 0,
          "losses": 0,
          "win_rate": null,
          "total_pnl": null,
          "avg_pnl": null,
          "avg_entry_price": null
        },
        "high": {
          "trades": 0,
          "wins": 0,
          "losses": 0,
          "win_rate": null,
          "total_pnl": null,
          "avg_pnl": null,
          "avg_entry_price": null
        },
        "unknown": {
          "trades": 0,
          "wins": 0,
          "losses": 0,
          "win_rate": null,
          "total_pnl": null,
          "avg_pnl": null,
          "avg_entry_price": null
        }
      },
      "DOWN": {
        "low": {
          "trades": 0,
          "wins": 0,
          "losses": 0,
          "win_rate": null,
          "total_pnl": null,
          "avg_pnl": null,
          "avg_entry_price": null
        },
        "medium": {
          "trades": 0,
          "wins": 0,
          "losses": 0,
          "win_rate": null,
          "total_pnl": null,
          "avg_pnl": null,
          "avg_entry_price": null
        },
        "high": {
          "trades": 0,
          "wins": 0,
          "losses": 0,
          "win_rate": null,
          "total_pnl": null,
          "avg_pnl": null,
          "avg_entry_price": null
        },
        "unknown": {
          "trades": 0,
          "wins": 0,
          "losses": 0,
          "win_rate": null,
          "total_pnl": null,
          "avg_pnl": null,
          "avg_entry_price": null
        }
      }
    },
    "unknown": {
      "UP": {
        "low": {
          "trades": 0,
          "wins": 0,
          "losses": 0,
          "win_rate": null,
          "total_pnl": null,
          "avg_pnl": null,
          "avg_entry_price": null
        },
        "medium": {
          "trades": 0,
          "wins": 0,
          "losses": 0,
          "win_rate": null,
          "total_pnl": null,
          "avg_pnl": null,
          "avg_entry_price": null
        },
        "high": {
          "trades": 0,
          "wins": 0,
          "losses": 0,
          "win_rate": null,
          "total_pnl": null,
          "avg_pnl": null,
          "avg_entry_price": null
        },
        "unknown": {
          "trades": 28,
          "wins": 14,
          "losses": 14,
          "win_rate": 0.5,
          "total_pnl": -8.4534,
          "avg_pnl": -0.3019071428571429,
          "avg_entry_price": 0.5603354497239684
        }
      },
      "DOWN": {
        "low": {
          "trades": 0,
          "wins": 0,
          "losses": 0,
          "win_rate": null,
          "total_pnl": null,
          "avg_pnl": null,
          "avg_entry_price": null
        },
        "medium": {
          "trades": 0,
          "wins": 0,
          "losses": 0,
          "win_rate": null,
          "total_pnl": null,
          "avg_pnl": null,
          "avg_entry_price": null
        },
        "high": {
          "trades": 0,
          "wins": 0,
          "losses": 0,
          "win_rate": null,
          "total_pnl": null,
          "avg_pnl": null,
          "avg_entry_price": null
        },
        "unknown": {
          "trades": 1,
          "wins": 1,
          "losses": 0,
          "win_rate": 1.0,
          "total_pnl": 2.4,
          "avg_pnl": 2.4,
          "avg_entry_price": 0.52
        }
      }
    }
  },
  "worst_trade_diagnostics": [
    {
      "market_id": "btc-updown-5m-1780262100",
      "direction": "UP",
      "entry_price": 0.65,
      "pnl": -3.25,
      "success": false,
      "actual_result": "UNKNOWN",
      "decision_timestamp": null,
      "d1_contribution": null,
      "d2_contribution": null,
      "d6_risk_level": "unknown",
      "d6_distance_shrinking": null,
      "d7_state": "missing",
      "d7_contribution": null,
      "score_gap": null,
      "confidence": null,
      "reject_reason": null,
      "final_block_reason": null
    },
    {
      "market_id": "btc-updown-5m-1780275000",
      "direction": "UP",
      "entry_price": 0.65,
      "pnl": -3.25,
      "success": false,
      "actual_result": "UNKNOWN",
      "decision_timestamp": null,
      "d1_contribution": null,
      "d2_contribution": null,
      "d6_risk_level": "unknown",
      "d6_distance_shrinking": null,
      "d7_state": "missing",
      "d7_contribution": null,
      "score_gap": null,
      "confidence": null,
      "reject_reason": null,
      "final_block_reason": null
    },
    {
      "market_id": "btc-updown-5m-1780323300",
      "direction": "UP",
      "entry_price": 0.65,
      "pnl": -3.25,
      "success": false,
      "actual_result": "UNKNOWN",
      "decision_timestamp": "2026-06-01T14:17:48.420088423Z",
      "d1_contribution": 2.0,
      "d2_contribution": 1.4,
      "d6_risk_level": "low",
      "d6_distance_shrinking": false,
      "d7_state": "active",
      "d7_contribution": 0.6000000000000001,
      "score_gap": 9.03,
      "confidence": 0.9029999999999999,
      "reject_reason": "",
      "final_block_reason": null
    },
    {
      "market_id": "btc-updown-5m-1780282200",
      "direction": "UP",
      "entry_price": 0.63,
      "pnl": -3.15,
      "success": false,
      "actual_result": "UNKNOWN",
      "decision_timestamp": null,
      "d1_contribution": null,
      "d2_contribution": null,
      "d6_risk_level": "unknown",
      "d6_distance_shrinking": null,
      "d7_state": "missing",
      "d7_contribution": null,
      "score_gap": null,
      "confidence": null,
      "reject_reason": null,
      "final_block_reason": null
    },
    {
      "market_id": "btc-updown-5m-1780282500",
      "direction": "UP",
      "entry_price": 0.63,
      "pnl": -3.15,
      "success": false,
      "actual_result": "UNKNOWN",
      "decision_timestamp": null,
      "d1_contribution": null,
      "d2_contribution": null,
      "d6_risk_level": "unknown",
      "d6_distance_shrinking": null,
      "d7_state": "missing",
      "d7_contribution": null,
      "score_gap": null,
      "confidence": null,
      "reject_reason": null,
      "final_block_reason": null
    },
    {
      "market_id": "btc-updown-5m-1780328400",
      "direction": "UP",
      "entry_price": 0.63,
      "pnl": -3.15,
      "success": false,
      "actual_result": "UNKNOWN",
      "decision_timestamp": "2026-06-01T15:42:51.319539319Z",
      "d1_contribution": 2.0,
      "d2_contribution": 1.4,
      "d6_risk_level": "low",
      "d6_distance_shrinking": false,
      "d7_state": "active",
      "d7_contribution": 0.6000000000000001,
      "score_gap": 8.355,
      "confidence": 0.8355,
      "reject_reason": "",
      "final_block_reason": null
    },
    {
      "market_id": "btc-updown-5m-1780253700",
      "direction": "UP",
      "entry_price": 0.61,
      "pnl": -3.05,
      "success": false,
      "actual_result": "UNKNOWN",
      "decision_timestamp": null,
      "d1_contribution": null,
      "d2_contribution": null,
      "d6_risk_level": "unknown",
      "d6_distance_shrinking": null,
      "d7_state": "missing",
      "d7_contribution": null,
      "score_gap": null,
      "confidence": null,
      "reject_reason": null,
      "final_block_reason": null
    },
    {
      "market_id": "btc-updown-5m-1780256400",
      "direction": "UP",
      "entry_price": 0.61,
      "pnl": -3.05,
      "success": false,
      "actual_result": "UNKNOWN",
      "decision_timestamp": null,
      "d1_contribution": null,
      "d2_contribution": null,
      "d6_risk_level": "unknown",
      "d6_distance_shrinking": null,
      "d7_state": "missing",
      "d7_contribution": null,
      "score_gap": null,
      "confidence": null,
      "reject_reason": null,
      "final_block_reason": null
    },
    {
      "market_id": "btc-updown-5m-1780371000",
      "direction": "UP",
      "entry_price": 0.6,
      "pnl": -3.0,
      "success": false,
      "actual_result": "UNKNOWN",
      "decision_timestamp": "2026-06-02T03:32:30.273964716Z",
      "d1_contribution": 1.097164264584732,
      "d2_contribution": 1.4,
      "d6_risk_level": "low",
      "d6_distance_shrinking": true,
      "d7_state": "active",
      "d7_contribution": 0.6000000000000001,
      "score_gap": 7.452164264584733,
      "confidence": 0.7452164264584733,
      "reject_reason": "",
      "final_block_reason": null
    },
    {
      "market_id": "btc-updown-5m-1780382400",
      "direction": "UP",
      "entry_price": 0.6,
      "pnl": -3.0,
      "success": false,
      "actual_result": "UNKNOWN",
      "decision_timestamp": "2026-06-02T06:42:30.274172746Z",
      "d1_contribution": 0.7527377572651672,
      "d2_contribution": 1.4,
      "d6_risk_level": "low",
      "d6_distance_shrinking": false,
      "d7_state": "active",
      "d7_contribution": 0.6000000000000001,
      "score_gap": 6.786738035574764,
      "confidence": 0.6786738035574764,
      "reject_reason": "",
      "final_block_reason": null
    },
    {
      "market_id": "btc-updown-5m-1780259400",
      "direction": "UP",
      "entry_price": 0.5599999999999999,
      "pnl": -2.8,
      "success": false,
      "actual_result": "UNKNOWN",
      "decision_timestamp": null,
      "d1_contribution": null,
      "d2_contribution": null,
      "d6_risk_level": "unknown",
      "d6_distance_shrinking": null,
      "d7_state": "missing",
      "d7_contribution": null,
      "score_gap": null,
      "confidence": null,
      "reject_reason": null,
      "final_block_reason": null
    },
    {
      "market_id": "btc-updown-5m-1780274100",
      "direction": "UP",
      "entry_price": 0.55,
      "pnl": -2.75,
      "success": false,
      "actual_result": "UNKNOWN",
      "decision_timestamp": null,
      "d1_contribution": null,
      "d2_contribution": null,
      "d6_risk_level": "unknown",
      "d6_distance_shrinking": null,
      "d7_state": "missing",
      "d7_contribution": null,
      "score_gap": null,
      "confidence": null,
      "reject_reason": null,
      "final_block_reason": null
    },
    {
      "market_id": "btc-updown-5m-1780259100",
      "direction": "UP",
      "entry_price": 0.53,
      "pnl": -2.6500000000000004,
      "success": false,
      "actual_result": "UNKNOWN",
      "decision_timestamp": null,
      "d1_contribution": null,
      "d2_contribution": null,
      "d6_risk_level": "unknown",
      "d6_distance_shrinking": null,
      "d7_state": "missing",
      "d7_contribution": null,
      "score_gap": null,
      "confidence": null,
      "reject_reason": null,
      "final_block_reason": null
    },
    {
      "market_id": "btc-updown-5m-1780250700",
      "direction": "UP",
      "entry_price": 0.49939999999999996,
      "pnl": -2.497,
      "success": false,
      "actual_result": "UNKNOWN",
      "decision_timestamp": null,
      "d1_contribution": null,
      "d2_contribution": null,
      "d6_risk_level": "unknown",
      "d6_distance_shrinking": null,
      "d7_state": "missing",
      "d7_contribution": null,
      "score_gap": null,
      "confidence": null,
      "reject_reason": null,
      "final_block_reason": null
    },
    {
      "market_id": "btc-updown-5m-1780277700",
      "direction": "UP",
      "entry_price": 0.49000000000000005,
      "pnl": -2.45,
      "success": false,
      "actual_result": "UNKNOWN",
      "decision_timestamp": null,
      "d1_contribution": null,
      "d2_contribution": null,
      "d6_risk_level": "unknown",
      "d6_distance_shrinking": null,
      "d7_state": "missing",
      "d7_contribution": null,
      "score_gap": null,
      "confidence": null,
      "reject_reason": null,
      "final_block_reason": null
    }
  ],
  "suspicious_entry_cluster_030_050": [
    {
      "market_id": "btc-updown-5m-1780250700",
      "direction": "UP",
      "entry_price": 0.49939999999999996,
      "pnl": -2.497,
      "success": false,
      "actual_result": "UNKNOWN",
      "decision_timestamp": null,
      "d1_contribution": null,
      "d2_contribution": null,
      "d6_risk_level": "unknown",
      "d6_distance_shrinking": null,
      "d7_state": "missing",
      "d7_contribution": null,
      "score_gap": null,
      "confidence": null,
      "reject_reason": null,
      "final_block_reason": null
    },
    {
      "market_id": "btc-updown-5m-1780277700",
      "direction": "UP",
      "entry_price": 0.49000000000000005,
      "pnl": -2.45,
      "success": false,
      "actual_result": "UNKNOWN",
      "decision_timestamp": null,
      "d1_contribution": null,
      "d2_contribution": null,
      "d6_risk_level": "unknown",
      "d6_distance_shrinking": null,
      "d7_state": "missing",
      "d7_contribution": null,
      "score_gap": null,
      "confidence": null,
      "reject_reason": null,
      "final_block_reason": null
    },
    {
      "market_id": "btc-updown-5m-1780251900",
      "direction": "UP",
      "entry_price": 0.48,
      "pnl": -2.4,
      "success": false,
      "actual_result": "UNKNOWN",
      "decision_timestamp": null,
      "d1_contribution": null,
      "d2_contribution": null,
      "d6_risk_level": "unknown",
      "d6_distance_shrinking": null,
      "d7_state": "missing",
      "d7_contribution": null,
      "score_gap": null,
      "confidence": null,
      "reject_reason": null,
      "final_block_reason": null
    },
    {
      "market_id": "btc-updown-5m-1780254000",
      "direction": "UP",
      "entry_price": 0.48,
      "pnl": -2.4,
      "success": false,
      "actual_result": "UNKNOWN",
      "decision_timestamp": null,
      "d1_contribution": null,
      "d2_contribution": null,
      "d6_risk_level": "unknown",
      "d6_distance_shrinking": null,
      "d7_state": "missing",
      "d7_contribution": null,
      "score_gap": null,
      "confidence": null,
      "reject_reason": null,
      "final_block_reason": null
    },
    {
      "market_id": "btc-updown-5m-1780317000",
      "direction": "UP",
      "entry_price": 0.48,
      "pnl": -2.4,
      "success": false,
      "actual_result": "UNKNOWN",
      "decision_timestamp": "2026-06-01T12:32:48.084388693Z",
      "d1_contribution": 1.8200682233158276,
      "d2_contribution": 1.4,
      "d6_risk_level": "low",
      "d6_distance_shrinking": false,
      "d7_state": "active",
      "d7_contribution": 0.6000000000000001,
      "score_gap": 8.175068223315828,
      "confidence": 0.8175068223315828,
      "reject_reason": "",
      "final_block_reason": null
    },
    {
      "market_id": "btc-updown-5m-1780324200",
      "direction": "UP",
      "entry_price": 0.46997999999999995,
      "pnl": -2.3499,
      "success": false,
      "actual_result": "UNKNOWN",
      "decision_timestamp": "2026-06-01T14:32:50.303490046Z",
      "d1_contribution": 2.0,
      "d2_contribution": 1.4,
      "d6_risk_level": "low",
      "d6_distance_shrinking": true,
      "d7_state": "active",
      "d7_contribution": 0.6000000000000001,
      "score_gap": 7.680000000000001,
      "confidence": 0.768,
      "reject_reason": "",
      "final_block_reason": null
    },
    {
      "market_id": "btc-updown-5m-1780327200",
      "direction": "UP",
      "entry_price": 0.44000000000000006,
      "pnl": -2.2,
      "success": false,
      "actual_result": "UNKNOWN",
      "decision_timestamp": "2026-06-01T15:22:45.512828953Z",
      "d1_contribution": 1.5040648570094381,
      "d2_contribution": 1.4,
      "d6_risk_level": "low",
      "d6_distance_shrinking": true,
      "d7_state": "active",
      "d7_contribution": 0.6000000000000001,
      "score_gap": 8.534064857009438,
      "confidence": 0.8534064857009438,
      "reject_reason": "",
      "final_block_reason": null
    },
    {
      "market_id": "btc-updown-5m-1780327500",
      "direction": "UP",
      "entry_price": 0.39,
      "pnl": -1.9500000000000002,
      "success": false,
      "actual_result": "UNKNOWN",
      "decision_timestamp": "2026-06-01T15:28:16.288417397Z",
      "d1_contribution": 2.0,
      "d2_contribution": 1.4,
      "d6_risk_level": "low",
      "d6_distance_shrinking": false,
      "d7_state": "neutral",
      "d7_contribution": 0.0,
      "score_gap": 7.754999999999999,
      "confidence": 0.7754999999999999,
      "reject_reason": "",
      "final_block_reason": null
    },
    {
      "market_id": "btc-updown-5m-1780365000",
      "direction": "UP",
      "entry_price": 0.33999999999999997,
      "pnl": -1.6999999999999997,
      "success": false,
      "actual_result": "UNKNOWN",
      "decision_timestamp": "2026-06-02T01:53:44.285984305Z",
      "d1_contribution": 2.0,
      "d2_contribution": 1.4,
      "d6_risk_level": "low",
      "d6_distance_shrinking": false,
      "d7_state": "active",
      "d7_contribution": 0.6000000000000001,
      "score_gap": 8.355,
      "confidence": 0.8355,
      "reject_reason": "",
      "final_block_reason": null
    },
    {
      "market_id": "btc-updown-5m-1780328100",
      "direction": "UP",
      "entry_price": 0.32,
      "pnl": -1.6,
      "success": false,
      "actual_result": "UNKNOWN",
      "decision_timestamp": "2026-06-01T15:38:15.889452545Z",
      "d1_contribution": 1.6075912829958976,
      "d2_contribution": 1.4,
      "d6_risk_level": "low",
      "d6_distance_shrinking": false,
      "d7_state": "active",
      "d7_contribution": 0.6000000000000001,
      "score_gap": 6.017591282995898,
      "confidence": 0.6017591282995898,
      "reject_reason": "",
      "final_block_reason": null
    }
  ],
  "reject_reasons": {
    "reject_reason_counts": {
      "spot_chainlink_disagreement": 4471,
      "ask_too_high": 3708,
      "insufficient_side_score": 2646,
      "mean_reversion_risk_high": 1863,
      "invalid_price_to_beat": 120,
      "rtds_unhealthy": 30,
      "unknown_result": 6,
      "no_selected_signal": 5,
      "risk_gate_blocked": 4
    },
    "final_block_reason_counts": {
      "Confidence below minimum floor": 4
    },
    "execution_precheck_failed_reason_counts": {
      "risk_gate_blocked": 4
    },
    "real_order_rejected_reason_counts": {},
    "highlighted_counts": {
      "mean_reversion_risk_high": 1863,
      "ask_too_low": 0,
      "ask_too_high": 3708,
      "direction_score_too_low": 0,
      "ev_too_low": 0
    }
  },
  "conclusions": [
    "D1/D2 contributions are strongly correlated; continue observing potential overlap.",
    "This report is diagnostic only and does not recommend automatic factor weight changes."
  ],
  "aligned_trades": [
    {
      "market_id": "btc-updown-5m-1780250700",
      "open_time": "2026-06-01T02:08:24.054170021+08:00",
      "entry_price": 0.49939999999999996,
      "direction": "UP",
      "actual_result": "UNKNOWN",
      "success": false,
      "pnl": -2.497,
      "decision_timestamp": null,
      "d6_risk_level": "unknown",
      "d6_distance_shrinking": null,
      "d7_state": "missing",
      "score_gap": null,
      "confidence": null,
      "reject_reason": null,
      "final_block_reason": null,
      "factors": {}
    },
    {
      "market_id": "btc-updown-5m-1780251000",
      "open_time": "2026-06-01T02:13:45.005854666+08:00",
      "entry_price": 0.65,
      "direction": "UP",
      "actual_result": "UP",
      "success": true,
      "pnl": 1.75,
      "decision_timestamp": null,
      "d6_risk_level": "unknown",
      "d6_distance_shrinking": null,
      "d7_state": "missing",
      "score_gap": null,
      "confidence": null,
      "reject_reason": null,
      "final_block_reason": null,
      "factors": {}
    },
    {
      "market_id": "btc-updown-5m-1780251900",
      "open_time": "2026-06-01T02:28:09.421872206+08:00",
      "entry_price": 0.48,
      "direction": "UP",
      "actual_result": "UNKNOWN",
      "success": false,
      "pnl": -2.4,
      "decision_timestamp": null,
      "d6_risk_level": "unknown",
      "d6_distance_shrinking": null,
      "d7_state": "missing",
      "score_gap": null,
      "confidence": null,
      "reject_reason": null,
      "final_block_reason": null,
      "factors": {}
    },
    {
      "market_id": "btc-updown-5m-1780253700",
      "open_time": "2026-06-01T02:58:37.870822168+08:00",
      "entry_price": 0.61,
      "direction": "UP",
      "actual_result": "UNKNOWN",
      "success": false,
      "pnl": -3.05,
      "decision_timestamp": null,
      "d6_risk_level": "unknown",
      "d6_distance_shrinking": null,
      "d7_state": "missing",
      "score_gap": null,
      "confidence": null,
      "reject_reason": null,
      "final_block_reason": null,
      "factors": {}
    },
    {
      "market_id": "btc-updown-5m-1780254000",
      "open_time": "2026-06-01T03:04:11.374819761+08:00",
      "entry_price": 0.48,
      "direction": "UP",
      "actual_result": "UNKNOWN",
      "success": false,
      "pnl": -2.4,
      "decision_timestamp": null,
      "d6_risk_level": "unknown",
      "d6_distance_shrinking": null,
      "d7_state": "missing",
      "score_gap": null,
      "confidence": null,
      "reject_reason": null,
      "final_block_reason": null,
      "factors": {}
    },
    {
      "market_id": "btc-updown-5m-1780254900",
      "open_time": "2026-06-01T03:18:24.702296325+08:00",
      "entry_price": 0.5999959929475878,
      "direction": "UP",
      "actual_result": "UP",
      "success": true,
      "pnl": 1.9965000000000002,
      "decision_timestamp": null,
      "d6_risk_level": "unknown",
      "d6_distance_shrinking": null,
      "d7_state": "missing",
      "score_gap": null,
      "confidence": null,
      "reject_reason": null,
      "final_block_reason": null,
      "factors": {}
    },
    {
      "market_id": "btc-updown-5m-1780256400",
      "open_time": "2026-06-01T03:43:57.500496203+08:00",
      "entry_price": 0.61,
      "direction": "UP",
      "actual_result": "UNKNOWN",
      "success": false,
      "pnl": -3.05,
      "decision_timestamp": null,
      "d6_risk_level": "unknown",
      "d6_distance_shrinking": null,
      "d7_state": "missing",
      "score_gap": null,
      "confidence": null,
      "reject_reason": null,
      "final_block_reason": null,
      "factors": {}
    },
    {
      "market_id": "btc-updown-5m-1780258800",
      "open_time": "2026-06-01T04:23:48.557684296+08:00",
      "entry_price": 0.21000000000000002,
      "direction": "UP",
      "actual_result": "UNKNOWN",
      "success": false,
      "pnl": -1.05,
      "decision_timestamp": null,
      "d6_risk_level": "unknown",
      "d6_distance_shrinking": null,
      "d7_state": "missing",
      "score_gap": null,
      "confidence": null,
      "reject_reason": null,
      "final_block_reason": null,
      "factors": {}
    },
    {
      "market_id": "btc-updown-5m-1780259100",
      "open_time": "2026-06-01T04:28:34.452023796+08:00",
      "entry_price": 0.53,
      "direction": "UP",
      "actual_result": "UNKNOWN",
      "success": false,
      "pnl": -2.6500000000000004,
      "decision_timestamp": null,
      "d6_risk_level": "unknown",
      "d6_distance_shrinking": null,
      "d7_state": "missing",
      "score_gap": null,
      "confidence": null,
      "reject_reason": null,
      "final_block_reason": null,
      "factors": {}
    },
    {
      "market_id": "btc-updown-5m-1780259400",
      "open_time": "2026-06-01T04:33:09.636124443+08:00",
      "entry_price": 0.5599999999999999,
      "direction": "UP",
      "actual_result": "UNKNOWN",
      "success": false,
      "pnl": -2.8,
      "decision_timestamp": null,
      "d6_risk_level": "unknown",
      "d6_distance_shrinking": null,
      "d7_state": "missing",
      "score_gap": null,
      "confidence": null,
      "reject_reason": null,
      "final_block_reason": null,
      "factors": {}
    },
    {
      "market_id": "btc-updown-5m-1780260300",
      "open_time": "2026-06-01T04:49:11.497822834+08:00",
      "entry_price": 0.639996799615954,
      "direction": "UP",
      "actual_result": "UP",
      "success": true,
      "pnl": 1.7997999999999994,
      "decision_timestamp": null,
      "d6_risk_level": "unknown",
      "d6_distance_shrinking": null,
      "d7_state": "missing",
      "score_gap": null,
      "confidence": null,
      "reject_reason": null,
      "final_block_reason": null,
      "factors": {}
    },
    {
      "market_id": "btc-updown-5m-1780262100",
      "open_time": "2026-06-01T05:18:45.763147028+08:00",
      "entry_price": 0.65,
      "direction": "UP",
      "actual_result": "UNKNOWN",
      "success": false,
      "pnl": -3.25,
      "decision_timestamp": null,
      "d6_risk_level": "unknown",
      "d6_distance_shrinking": null,
      "d7_state": "missing",
      "score_gap": null,
      "confidence": null,
      "reject_reason": null,
      "final_block_reason": null,
      "factors": {}
    },
    {
      "market_id": "btc-updown-5m-1780264200",
      "open_time": "2026-06-01T05:53:11.22622988+08:00",
      "entry_price": 0.53,
      "direction": "UP",
      "actual_result": "UP",
      "success": true,
      "pnl": 2.3499999999999996,
      "decision_timestamp": null,
      "d6_risk_level": "unknown",
      "d6_distance_shrinking": null,
      "d7_state": "missing",
      "score_gap": null,
      "confidence": null,
      "reject_reason": null,
      "final_block_reason": null,
      "factors": {}
    },
    {
      "market_id": "btc-updown-5m-1780267800",
      "open_time": "2026-06-01T06:53:25.013957275+08:00",
      "entry_price": 0.63,
      "direction": "UP",
      "actual_result": "UP",
      "success": true,
      "pnl": 1.85,
      "decision_timestamp": null,
      "d6_risk_level": "unknown",
      "d6_distance_shrinking": null,
      "d7_state": "missing",
      "score_gap": null,
      "confidence": null,
      "reject_reason": null,
      "final_block_reason": null,
      "factors": {}
    },
    {
      "market_id": "btc-updown-5m-1780269300",
      "open_time": "2026-06-01T07:18:17.625044754+08:00",
      "entry_price": 0.58,
      "direction": "UP",
      "actual_result": "UP",
      "success": true,
      "pnl": 2.1,
      "decision_timestamp": null,
      "d6_risk_level": "unknown",
      "d6_distance_shrinking": null,
      "d7_state": "missing",
      "score_gap": null,
      "confidence": null,
      "reject_reason": null,
      "final_block_reason": null,
      "factors": {}
    },
    {
      "market_id": "btc-updown-5m-1780269900",
      "open_time": "2026-06-01T07:28:11.997808388+08:00",
      "entry_price": 0.629999799707573,
      "direction": "UP",
      "actual_result": "UP",
      "success": true,
      "pnl": 1.8473000000000002,
      "decision_timestamp": null,
      "d6_risk_level": "unknown",
      "d6_distance_shrinking": null,
      "d7_state": "missing",
      "score_gap": null,
      "confidence": null,
      "reject_reason": null,
      "final_block_reason": null,
      "factors": {}
    },
    {
      "market_id": "btc-updown-5m-1780271700",
      "open_time": "2026-06-01T07:58:00.309087206+08:00",
      "entry_price": 0.65,
      "direction": "UP",
      "actual_result": "UP",
      "success": true,
      "pnl": 1.75,
      "decision_timestamp": null,
      "d6_risk_level": "unknown",
      "d6_distance_shrinking": null,
      "d7_state": "missing",
      "score_gap": null,
      "confidence": null,
      "reject_reason": null,
      "final_block_reason": null,
      "factors": {}
    },
    {
      "market_id": "btc-updown-5m-1780274100",
      "open_time": "2026-06-01T08:37:57.32779909+08:00",
      "entry_price": 0.55,
      "direction": "UP",
      "actual_result": "UNKNOWN",
      "success": false,
      "pnl": -2.75,
      "decision_timestamp": null,
      "d6_risk_level": "unknown",
      "d6_distance_shrinking": null,
      "d7_state": "missing",
      "score_gap": null,
      "confidence": null,
      "reject_reason": null,
      "final_block_reason": null,
      "factors": {}
    },
    {
      "market_id": "btc-updown-5m-1780275000",
      "open_time": "2026-06-01T08:53:01.638358958+08:00",
      "entry_price": 0.65,
      "direction": "UP",
      "actual_result": "UNKNOWN",
      "success": false,
      "pnl": -3.25,
      "decision_timestamp": null,
      "d6_risk_level": "unknown",
      "d6_distance_shrinking": null,
      "d7_state": "missing",
      "score_gap": null,
      "confidence": null,
      "reject_reason": null,
      "final_block_reason": null,
      "factors": {}
    },
    {
      "market_id": "btc-updown-5m-1780277400",
      "open_time": "2026-06-01T09:34:31.292939172+08:00",
      "entry_price": 0.55,
      "direction": "UP",
      "actual_result": "UP",
      "success": true,
      "pnl": 2.25,
      "decision_timestamp": null,
      "d6_risk_level": "unknown",
      "d6_distance_shrinking": null,
      "d7_state": "missing",
      "score_gap": null,
      "confidence": null,
      "reject_reason": null,
      "final_block_reason": null,
      "factors": {}
    },
    {
      "market_id": "btc-updown-5m-1780277700",
      "open_time": "2026-06-01T09:38:01.887137163+08:00",
      "entry_price": 0.49000000000000005,
      "direction": "UP",
      "actual_result": "UNKNOWN",
      "success": false,
      "pnl": -2.45,
      "decision_timestamp": null,
      "d6_risk_level": "unknown",
      "d6_distance_shrinking": null,
      "d7_state": "missing",
      "score_gap": null,
      "confidence": null,
      "reject_reason": null,
      "final_block_reason": null,
      "factors": {}
    },
    {
      "market_id": "btc-updown-5m-1780280700",
      "open_time": "2026-06-01T10:29:01.592940439+08:00",
      "entry_price": 0.25,
      "direction": "UP",
      "actual_result": "UP",
      "success": true,
      "pnl": 3.75,
      "decision_timestamp": null,
      "d6_risk_level": "unknown",
      "d6_distance_shrinking": null,
      "d7_state": "missing",
      "score_gap": null,
      "confidence": null,
      "reject_reason": null,
      "final_block_reason": null,
      "factors": {}
    },
    {
      "market_id": "btc-updown-5m-1780282200",
      "open_time": "2026-06-01T10:54:00.333256258+08:00",
      "entry_price": 0.63,
      "direction": "UP",
      "actual_result": "UNKNOWN",
      "success": false,
      "pnl": -3.15,
      "decision_timestamp": null,
      "d6_risk_level": "unknown",
      "d6_distance_shrinking": null,
      "d7_state": "missing",
      "score_gap": null,
      "confidence": null,
      "reject_reason": null,
      "final_block_reason": null,
      "factors": {}
    },
    {
      "market_id": "btc-updown-5m-1780282500",
      "open_time": "2026-06-01T10:59:32.109007148+08:00",
      "entry_price": 0.63,
      "direction": "UP",
      "actual_result": "UNKNOWN",
      "success": false,
      "pnl": -3.15,
      "decision_timestamp": null,
      "d6_risk_level": "unknown",
      "d6_distance_shrinking": null,
      "d7_state": "missing",
      "score_gap": null,
      "confidence": null,
      "reject_reason": null,
      "final_block_reason": null,
      "factors": {}
    },
    {
      "market_id": "btc-updown-5m-1780283100",
      "open_time": "2026-06-01T11:08:23.005028331+08:00",
      "entry_price": 0.6,
      "direction": "UP",
      "actual_result": "UP",
      "success": true,
      "pnl": 2.0,
      "decision_timestamp": null,
      "d6_risk_level": "unknown",
      "d6_distance_shrinking": null,
      "d7_state": "missing",
      "score_gap": null,
      "confidence": null,
      "reject_reason": null,
      "final_block_reason": null,
      "factors": {}
    },
    {
      "market_id": "btc-updown-5m-1780287900",
      "open_time": "2026-06-01T12:27:57.869761087+08:00",
      "entry_price": 0.52,
      "direction": "DOWN",
      "actual_result": "DOWN",
      "success": true,
      "pnl": 2.4,
      "decision_timestamp": null,
      "d6_risk_level": "unknown",
      "d6_distance_shrinking": null,
      "d7_state": "missing",
      "score_gap": null,
      "confidence": null,
      "reject_reason": null,
      "final_block_reason": null,
      "factors": {}
    },
    {
      "market_id": "btc-updown-5m-1780288500",
      "open_time": "2026-06-01T12:38:43.781704101+08:00",
      "entry_price": 0.61,
      "direction": "UP",
      "actual_result": "UP",
      "success": true,
      "pnl": 1.9500000000000002,
      "decision_timestamp": null,
      "d6_risk_level": "unknown",
      "d6_distance_shrinking": null,
      "d7_state": "missing",
      "score_gap": null,
      "confidence": null,
      "reject_reason": null,
      "final_block_reason": null,
      "factors": {}
    },
    {
      "market_id": "btc-updown-5m-1780295400",
      "open_time": "2026-06-01T14:32:58.541295433+08:00",
      "entry_price": 0.64,
      "direction": "UP",
      "actual_result": "UP",
      "success": true,
      "pnl": 1.7999999999999998,
      "decision_timestamp": null,
      "d6_risk_level": "unknown",
      "d6_distance_shrinking": null,
      "d7_state": "missing",
      "score_gap": null,
      "confidence": null,
      "reject_reason": null,
      "final_block_reason": null,
      "factors": {}
    },
    {
      "market_id": "btc-updown-5m-1780298700",
      "open_time": "2026-06-01T15:28:55.329392559+08:00",
      "entry_price": 0.55,
      "direction": "UP",
      "actual_result": "UP",
      "success": true,
      "pnl": 2.25,
      "decision_timestamp": null,
      "d6_risk_level": "unknown",
      "d6_distance_shrinking": null,
      "d7_state": "missing",
      "score_gap": null,
      "confidence": null,
      "reject_reason": null,
      "final_block_reason": null,
      "factors": {}
    },
    {
      "market_id": "btc-updown-5m-1780307700",
      "open_time": "2026-06-01T17:57:45.551719642+08:00",
      "entry_price": 0.54,
      "direction": "UP",
      "actual_result": "UP",
      "success": true,
      "pnl": 2.3,
      "decision_timestamp": "2026-06-01T09:57:34.101232609Z",
      "d6_risk_level": "low",
      "d6_distance_shrinking": false,
      "d7_state": "active",
      "score_gap": 6.882735315173008,
      "confidence": 0.6882735315173008,
      "reject_reason": "",
      "final_block_reason": null,
      "factors": {
        "D1": {
          "status": "active",
          "score_up": 0.5277353151730069,
          "score_down": 0.0,
          "signed_contribution": 0.5277353151730069,
          "abs_contribution": 0.5277353151730069,
          "configured_weight": null,
          "reason": null
        },
        "D2": {
          "status": "active",
          "score_up": 1.4,
          "score_down": 0.0,
          "signed_contribution": 1.4,
          "abs_contribution": 1.4,
          "configured_weight": null,
          "reason": null
        },
        "D3": {
          "status": "active",
          "score_up": 1.2,
          "score_down": 0.0,
          "signed_contribution": 1.2,
          "abs_contribution": 1.2,
          "configured_weight": null,
          "reason": null
        },
        "D4": {
          "status": "active",
          "score_up": 1.0,
          "score_down": 0.0,
          "signed_contribution": 1.0,
          "abs_contribution": 1.0,
          "configured_weight": null,
          "reason": null
        },
        "D5": {
          "status": "neutral",
          "score_up": 0.0,
          "score_down": 0.0,
          "signed_contribution": 0.0,
          "abs_contribution": 0.0,
          "configured_weight": null,
          "reason": null
        },
        "D6": {
          "status": "active",
          "score_up": 1.0499999999999998,
          "score_down": 0.0,
          "signed_contribution": 1.0499999999999998,
          "abs_contribution": 1.0499999999999998,
          "configured_weight": null,
          "reason": null
        },
        "D7": {
          "status": "active",
          "score_up": 0.6000000000000001,
          "score_down": 0.0,
          "signed_contribution": 0.6000000000000001,
          "abs_contribution": 0.6000000000000001,
          "configured_weight": null,
          "reason": null
        },
        "D8": {
          "status": "active",
          "score_up": 1.105,
          "score_down": 0.0,
          "signed_contribution": 1.105,
          "abs_contribution": 1.105,
          "configured_weight": null,
          "reason": null
        }
      }
    },
    {
      "market_id": "btc-updown-5m-1780316700",
      "open_time": "2026-06-01T20:28:03.017756092+08:00",
      "entry_price": 0.61,
      "direction": "UP",
      "actual_result": "UP",
      "success": true,
      "pnl": 1.9500000000000002,
      "decision_timestamp": "2026-06-01T12:27:46.377976356Z",
      "d6_risk_level": "low",
      "d6_distance_shrinking": false,
      "d7_state": "active",
      "score_gap": 6.988329432670735,
      "confidence": 0.6988329432670735,
      "reject_reason": "",
      "final_block_reason": null,
      "factors": {
        "D1": {
          "status": "active",
          "score_up": 2.0,
          "score_down": 0.0,
          "signed_contribution": 2.0,
          "abs_contribution": 2.0,
          "configured_weight": null,
          "reason": null
        },
        "D2": {
          "status": "active",
          "score_up": 1.4,
          "score_down": 0.0,
          "signed_contribution": 1.4,
          "abs_contribution": 1.4,
          "configured_weight": null,
          "reason": null
        },
        "D3": {
          "status": "neutral",
          "score_up": 0.0,
          "score_down": 0.0,
          "signed_contribution": 0.0,
          "abs_contribution": 0.0,
          "configured_weight": null,
          "reason": null
        },
        "D4": {
          "status": "active",
          "score_up": 0.8333294326707347,
          "score_down": 0.0,
          "signed_contribution": 0.8333294326707347,
          "abs_contribution": 0.8333294326707347,
          "configured_weight": null,
          "reason": null
        },
        "D5": {
          "status": "neutral",
          "score_up": 0.0,
          "score_down": 0.0,
          "signed_contribution": 0.0,
          "abs_contribution": 0.0,
          "configured_weight": null,
          "reason": null
        },
        "D6": {
          "status": "active",
          "score_up": 1.0499999999999998,
          "score_down": 0.0,
          "signed_contribution": 1.0499999999999998,
          "abs_contribution": 1.0499999999999998,
          "configured_weight": null,
          "reason": null
        },
        "D7": {
          "status": "active",
          "score_up": 0.6000000000000001,
          "score_down": 0.0,
          "signed_contribution": 0.6000000000000001,
          "abs_contribution": 0.6000000000000001,
          "configured_weight": null,
          "reason": null
        },
        "D8": {
          "status": "active",
          "score_up": 1.105,
          "score_down": 0.0,
          "signed_contribution": 1.105,
          "abs_contribution": 1.105,
          "configured_weight": null,
          "reason": null
        }
      }
    },
    {
      "market_id": "btc-updown-5m-1780317000",
      "open_time": "2026-06-01T20:33:02.957803843+08:00",
      "entry_price": 0.48,
      "direction": "UP",
      "actual_result": "UNKNOWN",
      "success": false,
      "pnl": -2.4,
      "decision_timestamp": "2026-06-01T12:32:48.084388693Z",
      "d6_risk_level": "low",
      "d6_distance_shrinking": false,
      "d7_state": "active",
      "score_gap": 8.175068223315828,
      "confidence": 0.8175068223315828,
      "reject_reason": "",
      "final_block_reason": null,
      "factors": {
        "D1": {
          "status": "active",
          "score_up": 1.8200682233158276,
          "score_down": 0.0,
          "signed_contribution": 1.8200682233158276,
          "abs_contribution": 1.8200682233158276,
          "configured_weight": null,
          "reason": null
        },
        "D2": {
          "status": "active",
          "score_up": 1.4,
          "score_down": 0.0,
          "signed_contribution": 1.4,
          "abs_contribution": 1.4,
          "configured_weight": null,
          "reason": null
        },
        "D3": {
          "status": "active",
          "score_up": 1.2,
          "score_down": 0.0,
          "signed_contribution": 1.2,
          "abs_contribution": 1.2,
          "configured_weight": null,
          "reason": null
        },
        "D4": {
          "status": "active",
          "score_up": 1.0,
          "score_down": 0.0,
          "signed_contribution": 1.0,
          "abs_contribution": 1.0,
          "configured_weight": null,
          "reason": null
        },
        "D5": {
          "status": "neutral",
          "score_up": 0.0,
          "score_down": 0.0,
          "signed_contribution": 0.0,
          "abs_contribution": 0.0,
          "configured_weight": null,
          "reason": null
        },
        "D6": {
          "status": "active",
          "score_up": 1.0499999999999998,
          "score_down": 0.0,
          "signed_contribution": 1.0499999999999998,
          "abs_contribution": 1.0499999999999998,
          "configured_weight": null,
          "reason": null
        },
        "D7": {
          "status": "active",
          "score_up": 0.6000000000000001,
          "score_down": 0.0,
          "signed_contribution": 0.6000000000000001,
          "abs_contribution": 0.6000000000000001,
          "configured_weight": null,
          "reason": null
        },
        "D8": {
          "status": "active",
          "score_up": 1.105,
          "score_down": 0.0,
          "signed_contribution": 1.105,
          "abs_contribution": 1.105,
          "configured_weight": null,
          "reason": null
        }
      }
    },
    {
      "market_id": "btc-updown-5m-1780320300",
      "open_time": "2026-06-01T21:28:05.220784559+08:00",
      "entry_price": 0.63,
      "direction": "UP",
      "actual_result": "UP",
      "success": true,
      "pnl": 1.85,
      "decision_timestamp": "2026-06-01T13:27:48.80414029Z",
      "d6_risk_level": "low",
      "d6_distance_shrinking": false,
      "d7_state": "active",
      "score_gap": 7.680000000000001,
      "confidence": 0.768,
      "reject_reason": "",
      "final_block_reason": null,
      "factors": {
        "D1": {
          "status": "active",
          "score_up": 2.0,
          "score_down": 0.0,
          "signed_contribution": 2.0,
          "abs_contribution": 2.0,
          "configured_weight": null,
          "reason": null
        },
        "D2": {
          "status": "active",
          "score_up": 1.4,
          "score_down": 0.0,
          "signed_contribution": 1.4,
          "abs_contribution": 1.4,
          "configured_weight": null,
          "reason": null
        },
        "D3": {
          "status": "active",
          "score_up": 1.2,
          "score_down": 0.0,
          "signed_contribution": 1.2,
          "abs_contribution": 1.2,
          "configured_weight": null,
          "reason": null
        },
        "D4": {
          "status": "active",
          "score_up": 1.0,
          "score_down": 0.0,
          "signed_contribution": 1.0,
          "abs_contribution": 1.0,
          "configured_weight": null,
          "reason": null
        },
        "D5": {
          "status": "active",
          "score_up": 0.0,
          "score_down": 0.675,
          "signed_contribution": -0.675,
          "abs_contribution": 0.675,
          "configured_weight": null,
          "reason": null
        },
        "D6": {
          "status": "active",
          "score_up": 1.0499999999999998,
          "score_down": 0.0,
          "signed_contribution": 1.0499999999999998,
          "abs_contribution": 1.0499999999999998,
          "configured_weight": null,
          "reason": null
        },
        "D7": {
          "status": "active",
          "score_up": 0.6000000000000001,
          "score_down": 0.0,
          "signed_contribution": 0.6000000000000001,
          "abs_contribution": 0.6000000000000001,
          "configured_weight": null,
          "reason": null
        },
        "D8": {
          "status": "active",
          "score_up": 1.105,
          "score_down": 0.0,
          "signed_contribution": 1.105,
          "abs_contribution": 1.105,
          "configured_weight": null,
          "reason": null
        }
      }
    },
    {
      "market_id": "btc-updown-5m-1780323300",
      "open_time": "2026-06-01T22:17:59.72539788+08:00",
      "entry_price": 0.65,
      "direction": "UP",
      "actual_result": "UNKNOWN",
      "success": false,
      "pnl": -3.25,
      "decision_timestamp": "2026-06-01T14:17:48.420088423Z",
      "d6_risk_level": "low",
      "d6_distance_shrinking": false,
      "d7_state": "active",
      "score_gap": 9.03,
      "confidence": 0.9029999999999999,
      "reject_reason": "",
      "final_block_reason": null,
      "factors": {
        "D1": {
          "status": "active",
          "score_up": 2.0,
          "score_down": 0.0,
          "signed_contribution": 2.0,
          "abs_contribution": 2.0,
          "configured_weight": null,
          "reason": null
        },
        "D2": {
          "status": "active",
          "score_up": 1.4,
          "score_down": 0.0,
          "signed_contribution": 1.4,
          "abs_contribution": 1.4,
          "configured_weight": null,
          "reason": null
        },
        "D3": {
          "status": "active",
          "score_up": 1.2,
          "score_down": 0.0,
          "signed_contribution": 1.2,
          "abs_contribution": 1.2,
          "configured_weight": null,
          "reason": null
        },
        "D4": {
          "status": "active",
          "score_up": 1.0,
          "score_down": 0.0,
          "signed_contribution": 1.0,
          "abs_contribution": 1.0,
          "configured_weight": null,
          "reason": null
        },
        "D5": {
          "status": "active",
          "score_up": 0.675,
          "score_down": 0.0,
          "signed_contribution": 0.675,
          "abs_contribution": 0.675,
          "configured_weight": null,
          "reason": null
        },
        "D6": {
          "status": "active",
          "score_up": 1.0499999999999998,
          "score_down": 0.0,
          "signed_contribution": 1.0499999999999998,
          "abs_contribution": 1.0499999999999998,
          "configured_weight": null,
          "reason": null
        },
        "D7": {
          "status": "active",
          "score_up": 0.6000000000000001,
          "score_down": 0.0,
          "signed_contribution": 0.6000000000000001,
          "abs_contribution": 0.6000000000000001,
          "configured_weight": null,
          "reason": null
        },
        "D8": {
          "status": "active",
          "score_up": 1.105,
          "score_down": 0.0,
          "signed_contribution": 1.105,
          "abs_contribution": 1.105,
          "configured_weight": null,
          "reason": null
        }
      }
    },
    {
      "market_id": "btc-updown-5m-1780323600",
      "open_time": "2026-06-01T22:22:40.657196507+08:00",
      "entry_price": 0.5599999999999999,
      "direction": "UP",
      "actual_result": "UP",
      "success": true,
      "pnl": 2.2,
      "decision_timestamp": "2026-06-01T14:22:30.31571238Z",
      "d6_risk_level": "low",
      "d6_distance_shrinking": false,
      "d7_state": "active",
      "score_gap": 8.355,
      "confidence": 0.8355,
      "reject_reason": "",
      "final_block_reason": null,
      "factors": {
        "D1": {
          "status": "active",
          "score_up": 2.0,
          "score_down": 0.0,
          "signed_contribution": 2.0,
          "abs_contribution": 2.0,
          "configured_weight": null,
          "reason": null
        },
        "D2": {
          "status": "active",
          "score_up": 1.4,
          "score_down": 0.0,
          "signed_contribution": 1.4,
          "abs_contribution": 1.4,
          "configured_weight": null,
          "reason": null
        },
        "D3": {
          "status": "active",
          "score_up": 1.2,
          "score_down": 0.0,
          "signed_contribution": 1.2,
          "abs_contribution": 1.2,
          "configured_weight": null,
          "reason": null
        },
        "D4": {
          "status": "active",
          "score_up": 1.0,
          "score_down": 0.0,
          "signed_contribution": 1.0,
          "abs_contribution": 1.0,
          "configured_weight": null,
          "reason": null
        },
        "D5": {
          "status": "neutral",
          "score_up": 0.0,
          "score_down": 0.0,
          "signed_contribution": 0.0,
          "abs_contribution": 0.0,
          "configured_weight": null,
          "reason": null
        },
        "D6": {
          "status": "active",
          "score_up": 1.0499999999999998,
          "score_down": 0.0,
          "signed_contribution": 1.0499999999999998,
          "abs_contribution": 1.0499999999999998,
          "configured_weight": null,
          "reason": null
        },
        "D7": {
          "status": "active",
          "score_up": 0.6000000000000001,
          "score_down": 0.0,
          "signed_contribution": 0.6000000000000001,
          "abs_contribution": 0.6000000000000001,
          "configured_weight": null,
          "reason": null
        },
        "D8": {
          "status": "active",
          "score_up": 1.105,
          "score_down": 0.0,
          "signed_contribution": 1.105,
          "abs_contribution": 1.105,
          "configured_weight": null,
          "reason": null
        }
      }
    },
    {
      "market_id": "btc-updown-5m-1780324200",
      "open_time": "2026-06-01T22:33:03.616025075+08:00",
      "entry_price": 0.46997999999999995,
      "direction": "UP",
      "actual_result": "UNKNOWN",
      "success": false,
      "pnl": -2.3499,
      "decision_timestamp": "2026-06-01T14:32:50.303490046Z",
      "d6_risk_level": "low",
      "d6_distance_shrinking": true,
      "d7_state": "active",
      "score_gap": 7.680000000000001,
      "confidence": 0.768,
      "reject_reason": "",
      "final_block_reason": null,
      "factors": {
        "D1": {
          "status": "active",
          "score_up": 2.0,
          "score_down": 0.0,
          "signed_contribution": 2.0,
          "abs_contribution": 2.0,
          "configured_weight": null,
          "reason": null
        },
        "D2": {
          "status": "active",
          "score_up": 1.4,
          "score_down": 0.0,
          "signed_contribution": 1.4,
          "abs_contribution": 1.4,
          "configured_weight": null,
          "reason": null
        },
        "D3": {
          "status": "active",
          "score_up": 1.2,
          "score_down": 0.0,
          "signed_contribution": 1.2,
          "abs_contribution": 1.2,
          "configured_weight": null,
          "reason": null
        },
        "D4": {
          "status": "active",
          "score_up": 1.0,
          "score_down": 0.0,
          "signed_contribution": 1.0,
          "abs_contribution": 1.0,
          "configured_weight": null,
          "reason": null
        },
        "D5": {
          "status": "active",
          "score_up": 0.0,
          "score_down": 0.675,
          "signed_contribution": -0.675,
          "abs_contribution": 0.675,
          "configured_weight": null,
          "reason": null
        },
        "D6": {
          "status": "active",
          "score_up": 1.0499999999999998,
          "score_down": 0.0,
          "signed_contribution": 1.0499999999999998,
          "abs_contribution": 1.0499999999999998,
          "configured_weight": null,
          "reason": null
        },
        "D7": {
          "status": "active",
          "score_up": 0.6000000000000001,
          "score_down": 0.0,
          "signed_contribution": 0.6000000000000001,
          "abs_contribution": 0.6000000000000001,
          "configured_weight": null,
          "reason": null
        },
        "D8": {
          "status": "active",
          "score_up": 1.105,
          "score_down": 0.0,
          "signed_contribution": 1.105,
          "abs_contribution": 1.105,
          "configured_weight": null,
          "reason": null
        }
      }
    },
    {
      "market_id": "btc-updown-5m-1780325100",
      "open_time": "2026-06-01T22:48:01.87242428+08:00",
      "entry_price": 0.54,
      "direction": "UP",
      "actual_result": "UP",
      "success": true,
      "pnl": 2.3,
      "decision_timestamp": "2026-06-01T14:47:47.303299161Z",
      "d6_risk_level": "low",
      "d6_distance_shrinking": false,
      "d7_state": "neutral",
      "score_gap": 6.871906280255766,
      "confidence": 0.6871906280255766,
      "reject_reason": "",
      "final_block_reason": null,
      "factors": {
        "D1": {
          "status": "active",
          "score_up": 2.0,
          "score_down": 0.0,
          "signed_contribution": 2.0,
          "abs_contribution": 2.0,
          "configured_weight": null,
          "reason": null
        },
        "D2": {
          "status": "active",
          "score_up": 1.4,
          "score_down": 0.0,
          "signed_contribution": 1.4,
          "abs_contribution": 1.4,
          "configured_weight": null,
          "reason": null
        },
        "D3": {
          "status": "active",
          "score_up": 0.0,
          "score_down": 0.0663136423822766,
          "signed_contribution": -0.0663136423822766,
          "abs_contribution": 0.0663136423822766,
          "configured_weight": null,
          "reason": null
        },
        "D4": {
          "status": "active",
          "score_up": 0.7082199226380433,
          "score_down": 0.0,
          "signed_contribution": 0.7082199226380433,
          "abs_contribution": 0.7082199226380433,
          "configured_weight": null,
          "reason": null
        },
        "D5": {
          "status": "active",
          "score_up": 0.675,
          "score_down": 0.0,
          "signed_contribution": 0.675,
          "abs_contribution": 0.675,
          "configured_weight": null,
          "reason": null
        },
        "D6": {
          "status": "active",
          "score_up": 1.0499999999999998,
          "score_down": 0.0,
          "signed_contribution": 1.0499999999999998,
          "abs_contribution": 1.0499999999999998,
          "configured_weight": null,
          "reason": null
        },
        "D7": {
          "status": "neutral",
          "score_up": 0.0,
          "score_down": 0.0,
          "signed_contribution": 0.0,
          "abs_contribution": 0.0,
          "configured_weight": null,
          "reason": null
        },
        "D8": {
          "status": "active",
          "score_up": 1.105,
          "score_down": 0.0,
          "signed_contribution": 1.105,
          "abs_contribution": 1.105,
          "configured_weight": null,
          "reason": null
        }
      }
    },
    {
      "market_id": "btc-updown-5m-1780327200",
      "open_time": "2026-06-01T23:22:57.621727571+08:00",
      "entry_price": 0.44000000000000006,
      "direction": "UP",
      "actual_result": "UNKNOWN",
      "success": false,
      "pnl": -2.2,
      "decision_timestamp": "2026-06-01T15:22:45.512828953Z",
      "d6_risk_level": "low",
      "d6_distance_shrinking": true,
      "d7_state": "active",
      "score_gap": 8.534064857009438,
      "confidence": 0.8534064857009438,
      "reject_reason": "",
      "final_block_reason": null,
      "factors": {
        "D1": {
          "status": "active",
          "score_up": 1.5040648570094381,
          "score_down": 0.0,
          "signed_contribution": 1.5040648570094381,
          "abs_contribution": 1.5040648570094381,
          "configured_weight": null,
          "reason": null
        },
        "D2": {
          "status": "active",
          "score_up": 1.4,
          "score_down": 0.0,
          "signed_contribution": 1.4,
          "abs_contribution": 1.4,
          "configured_weight": null,
          "reason": null
        },
        "D3": {
          "status": "active",
          "score_up": 1.2,
          "score_down": 0.0,
          "signed_contribution": 1.2,
          "abs_contribution": 1.2,
          "configured_weight": null,
          "reason": null
        },
        "D4": {
          "status": "active",
          "score_up": 1.0,
          "score_down": 0.0,
          "signed_contribution": 1.0,
          "abs_contribution": 1.0,
          "configured_weight": null,
          "reason": null
        },
        "D5": {
          "status": "active",
          "score_up": 0.675,
          "score_down": 0.0,
          "signed_contribution": 0.675,
          "abs_contribution": 0.675,
          "configured_weight": null,
          "reason": null
        },
        "D6": {
          "status": "active",
          "score_up": 1.0499999999999998,
          "score_down": 0.0,
          "signed_contribution": 1.0499999999999998,
          "abs_contribution": 1.0499999999999998,
          "configured_weight": null,
          "reason": null
        },
        "D7": {
          "status": "active",
          "score_up": 0.6000000000000001,
          "score_down": 0.0,
          "signed_contribution": 0.6000000000000001,
          "abs_contribution": 0.6000000000000001,
          "configured_weight": null,
          "reason": null
        },
        "D8": {
          "status": "active",
          "score_up": 1.105,
          "score_down": 0.0,
          "signed_contribution": 1.105,
          "abs_contribution": 1.105,
          "configured_weight": null,
          "reason": null
        }
      }
    },
    {
      "market_id": "btc-updown-5m-1780327500",
      "open_time": "2026-06-01T23:28:32.523445205+08:00",
      "entry_price": 0.39,
      "direction": "UP",
      "actual_result": "UNKNOWN",
      "success": false,
      "pnl": -1.9500000000000002,
      "decision_timestamp": "2026-06-01T15:28:16.288417397Z",
      "d6_risk_level": "low",
      "d6_distance_shrinking": false,
      "d7_state": "neutral",
      "score_gap": 7.754999999999999,
      "confidence": 0.7754999999999999,
      "reject_reason": "",
      "final_block_reason": null,
      "factors": {
        "D1": {
          "status": "active",
          "score_up": 2.0,
          "score_down": 0.0,
          "signed_contribution": 2.0,
          "abs_contribution": 2.0,
          "configured_weight": null,
          "reason": null
        },
        "D2": {
          "status": "active",
          "score_up": 1.4,
          "score_down": 0.0,
          "signed_contribution": 1.4,
          "abs_contribution": 1.4,
          "configured_weight": null,
          "reason": null
        },
        "D3": {
          "status": "active",
          "score_up": 1.2,
          "score_down": 0.0,
          "signed_contribution": 1.2,
          "abs_contribution": 1.2,
          "configured_weight": null,
          "reason": null
        },
        "D4": {
          "status": "active",
          "score_up": 1.0,
          "score_down": 0.0,
          "signed_contribution": 1.0,
          "abs_contribution": 1.0,
          "configured_weight": null,
          "reason": null
        },
        "D5": {
          "status": "neutral",
          "score_up": 0.0,
          "score_down": 0.0,
          "signed_contribution": 0.0,
          "abs_contribution": 0.0,
          "configured_weight": null,
          "reason": null
        },
        "D6": {
          "status": "active",
          "score_up": 1.0499999999999998,
          "score_down": 0.0,
          "signed_contribution": 1.0499999999999998,
          "abs_contribution": 1.0499999999999998,
          "configured_weight": null,
          "reason": null
        },
        "D7": {
          "status": "neutral",
          "score_up": 0.0,
          "score_down": 0.0,
          "signed_contribution": 0.0,
          "abs_contribution": 0.0,
          "configured_weight": null,
          "reason": null
        },
        "D8": {
          "status": "active",
          "score_up": 1.105,
          "score_down": 0.0,
          "signed_contribution": 1.105,
          "abs_contribution": 1.105,
          "configured_weight": null,
          "reason": null
        }
      }
    },
    {
      "market_id": "btc-updown-5m-1780328100",
      "open_time": "2026-06-01T23:38:26.224254568+08:00",
      "entry_price": 0.32,
      "direction": "UP",
      "actual_result": "UNKNOWN",
      "success": false,
      "pnl": -1.6,
      "decision_timestamp": "2026-06-01T15:38:15.889452545Z",
      "d6_risk_level": "low",
      "d6_distance_shrinking": false,
      "d7_state": "active",
      "score_gap": 6.017591282995898,
      "confidence": 0.6017591282995898,
      "reject_reason": "",
      "final_block_reason": null,
      "factors": {
        "D1": {
          "status": "active",
          "score_up": 1.6075912829958976,
          "score_down": 0.0,
          "signed_contribution": 1.6075912829958976,
          "abs_contribution": 1.6075912829958976,
          "configured_weight": null,
          "reason": null
        },
        "D2": {
          "status": "active",
          "score_up": 1.4,
          "score_down": 0.0,
          "signed_contribution": 1.4,
          "abs_contribution": 1.4,
          "configured_weight": null,
          "reason": null
        },
        "D3": {
          "status": "active",
          "score_up": 0.0,
          "score_down": 0.42,
          "signed_contribution": -0.42,
          "abs_contribution": 0.42,
          "configured_weight": null,
          "reason": null
        },
        "D4": {
          "status": "neutral",
          "score_up": 0.0,
          "score_down": 0.0,
          "signed_contribution": 0.0,
          "abs_contribution": 0.0,
          "configured_weight": null,
          "reason": null
        },
        "D5": {
          "status": "active",
          "score_up": 0.675,
          "score_down": 0.0,
          "signed_contribution": 0.675,
          "abs_contribution": 0.675,
          "configured_weight": null,
          "reason": null
        },
        "D6": {
          "status": "active",
          "score_up": 1.0499999999999998,
          "score_down": 0.0,
          "signed_contribution": 1.0499999999999998,
          "abs_contribution": 1.0499999999999998,
          "configured_weight": null,
          "reason": null
        },
        "D7": {
          "status": "active",
          "score_up": 0.6000000000000001,
          "score_down": 0.0,
          "signed_contribution": 0.6000000000000001,
          "abs_contribution": 0.6000000000000001,
          "configured_weight": null,
          "reason": null
        },
        "D8": {
          "status": "active",
          "score_up": 1.105,
          "score_down": 0.0,
          "signed_contribution": 1.105,
          "abs_contribution": 1.105,
          "configured_weight": null,
          "reason": null
        }
      }
    },
    {
      "market_id": "btc-updown-5m-1780328400",
      "open_time": "2026-06-01T23:43:03.537766192+08:00",
      "entry_price": 0.63,
      "direction": "UP",
      "actual_result": "UNKNOWN",
      "success": false,
      "pnl": -3.15,
      "decision_timestamp": "2026-06-01T15:42:51.319539319Z",
      "d6_risk_level": "low",
      "d6_distance_shrinking": false,
      "d7_state": "active",
      "score_gap": 8.355,
      "confidence": 0.8355,
      "reject_reason": "",
      "final_block_reason": null,
      "factors": {
        "D1": {
          "status": "active",
          "score_up": 2.0,
          "score_down": 0.0,
          "signed_contribution": 2.0,
          "abs_contribution": 2.0,
          "configured_weight": null,
          "reason": null
        },
        "D2": {
          "status": "active",
          "score_up": 1.4,
          "score_down": 0.0,
          "signed_contribution": 1.4,
          "abs_contribution": 1.4,
          "configured_weight": null,
          "reason": null
        },
        "D3": {
          "status": "active",
          "score_up": 1.2,
          "score_down": 0.0,
          "signed_contribution": 1.2,
          "abs_contribution": 1.2,
          "configured_weight": null,
          "reason": null
        },
        "D4": {
          "status": "active",
          "score_up": 1.0,
          "score_down": 0.0,
          "signed_contribution": 1.0,
          "abs_contribution": 1.0,
          "configured_weight": null,
          "reason": null
        },
        "D5": {
          "status": "neutral",
          "score_up": 0.0,
          "score_down": 0.0,
          "signed_contribution": 0.0,
          "abs_contribution": 0.0,
          "configured_weight": null,
          "reason": null
        },
        "D6": {
          "status": "active",
          "score_up": 1.0499999999999998,
          "score_down": 0.0,
          "signed_contribution": 1.0499999999999998,
          "abs_contribution": 1.0499999999999998,
          "configured_weight": null,
          "reason": null
        },
        "D7": {
          "status": "active",
          "score_up": 0.6000000000000001,
          "score_down": 0.0,
          "signed_contribution": 0.6000000000000001,
          "abs_contribution": 0.6000000000000001,
          "configured_weight": null,
          "reason": null
        },
        "D8": {
          "status": "active",
          "score_up": 1.105,
          "score_down": 0.0,
          "signed_contribution": 1.105,
          "abs_contribution": 1.105,
          "configured_weight": null,
          "reason": null
        }
      }
    },
    {
      "market_id": "btc-updown-5m-1780365000",
      "open_time": "2026-06-02T09:53:55.543884507+08:00",
      "entry_price": 0.33999999999999997,
      "direction": "UP",
      "actual_result": "UNKNOWN",
      "success": false,
      "pnl": -1.6999999999999997,
      "decision_timestamp": "2026-06-02T01:53:44.285984305Z",
      "d6_risk_level": "low",
      "d6_distance_shrinking": false,
      "d7_state": "active",
      "score_gap": 8.355,
      "confidence": 0.8355,
      "reject_reason": "",
      "final_block_reason": null,
      "factors": {
        "D1": {
          "status": "active",
          "score_up": 2.0,
          "score_down": 0.0,
          "signed_contribution": 2.0,
          "abs_contribution": 2.0,
          "configured_weight": null,
          "reason": null
        },
        "D2": {
          "status": "active",
          "score_up": 1.4,
          "score_down": 0.0,
          "signed_contribution": 1.4,
          "abs_contribution": 1.4,
          "configured_weight": null,
          "reason": null
        },
        "D3": {
          "status": "active",
          "score_up": 1.2,
          "score_down": 0.0,
          "signed_contribution": 1.2,
          "abs_contribution": 1.2,
          "configured_weight": null,
          "reason": null
        },
        "D4": {
          "status": "active",
          "score_up": 1.0,
          "score_down": 0.0,
          "signed_contribution": 1.0,
          "abs_contribution": 1.0,
          "configured_weight": null,
          "reason": null
        },
        "D5": {
          "status": "neutral",
          "score_up": 0.0,
          "score_down": 0.0,
          "signed_contribution": 0.0,
          "abs_contribution": 0.0,
          "configured_weight": null,
          "reason": null
        },
        "D6": {
          "status": "active",
          "score_up": 1.0499999999999998,
          "score_down": 0.0,
          "signed_contribution": 1.0499999999999998,
          "abs_contribution": 1.0499999999999998,
          "configured_weight": null,
          "reason": null
        },
        "D7": {
          "status": "active",
          "score_up": 0.6000000000000001,
          "score_down": 0.0,
          "signed_contribution": 0.6000000000000001,
          "abs_contribution": 0.6000000000000001,
          "configured_weight": null,
          "reason": null
        },
        "D8": {
          "status": "active",
          "score_up": 1.105,
          "score_down": 0.0,
          "signed_contribution": 1.105,
          "abs_contribution": 1.105,
          "configured_weight": null,
          "reason": null
        }
      }
    },
    {
      "market_id": "btc-updown-5m-1780369200",
      "open_time": "2026-06-02T11:03:09.234063556+08:00",
      "entry_price": 0.65,
      "direction": "UP",
      "actual_result": "UP",
      "success": true,
      "pnl": 1.75,
      "decision_timestamp": "2026-06-02T03:02:56.274163652Z",
      "d6_risk_level": "medium",
      "d6_distance_shrinking": true,
      "d7_state": "neutral",
      "score_gap": 6.936583847583234,
      "confidence": 0.6936583847583234,
      "reject_reason": "",
      "final_block_reason": null,
      "factors": {
        "D1": {
          "status": "active",
          "score_up": 1.9329158824067938,
          "score_down": 0.0,
          "signed_contribution": 1.9329158824067938,
          "abs_contribution": 1.9329158824067938,
          "configured_weight": null,
          "reason": null
        },
        "D2": {
          "status": "active",
          "score_up": 1.4,
          "score_down": 0.0,
          "signed_contribution": 1.4,
          "abs_contribution": 1.4,
          "configured_weight": null,
          "reason": null
        },
        "D3": {
          "status": "active",
          "score_up": 0.9795150214207506,
          "score_down": 0.0,
          "signed_contribution": 0.9795150214207506,
          "abs_contribution": 0.9795150214207506,
          "configured_weight": null,
          "reason": null
        },
        "D4": {
          "status": "active",
          "score_up": 0.8441529437556897,
          "score_down": 0.0,
          "signed_contribution": 0.8441529437556897,
          "abs_contribution": 0.8441529437556897,
          "configured_weight": null,
          "reason": null
        },
        "D5": {
          "status": "active",
          "score_up": 0.675,
          "score_down": 0.0,
          "signed_contribution": 0.675,
          "abs_contribution": 0.675,
          "configured_weight": null,
          "reason": null
        },
        "D6": {
          "status": "neutral",
          "score_up": 0.0,
          "score_down": 0.0,
          "signed_contribution": 0.0,
          "abs_contribution": 0.0,
          "configured_weight": null,
          "reason": null
        },
        "D7": {
          "status": "neutral",
          "score_up": 0.0,
          "score_down": 0.0,
          "signed_contribution": 0.0,
          "abs_contribution": 0.0,
          "configured_weight": null,
          "reason": null
        },
        "D8": {
          "status": "active",
          "score_up": 1.105,
          "score_down": 0.0,
          "signed_contribution": 1.105,
          "abs_contribution": 1.105,
          "configured_weight": null,
          "reason": null
        }
      }
    },
    {
      "market_id": "btc-updown-5m-1780370400",
      "open_time": "2026-06-02T11:23:03.123409697+08:00",
      "entry_price": 0.5599999999999999,
      "direction": "UP",
      "actual_result": "UP",
      "success": true,
      "pnl": 2.2,
      "decision_timestamp": "2026-06-02T03:22:53.775580542Z",
      "d6_risk_level": "low",
      "d6_distance_shrinking": true,
      "d7_state": "active",
      "score_gap": 6.654079640486058,
      "confidence": 0.6654079640486058,
      "reject_reason": "",
      "final_block_reason": null,
      "factors": {
        "D1": {
          "status": "active",
          "score_up": 0.046848394598888454,
          "score_down": 0.0,
          "signed_contribution": 0.046848394598888454,
          "abs_contribution": 0.046848394598888454,
          "configured_weight": null,
          "reason": null
        },
        "D2": {
          "status": "active",
          "score_up": 0.9772312458871689,
          "score_down": 0.0,
          "signed_contribution": 0.9772312458871689,
          "abs_contribution": 0.9772312458871689,
          "configured_weight": null,
          "reason": null
        },
        "D3": {
          "status": "active",
          "score_up": 1.2,
          "score_down": 0.0,
          "signed_contribution": 1.2,
          "abs_contribution": 1.2,
          "configured_weight": null,
          "reason": null
        },
        "D4": {
          "status": "active",
          "score_up": 1.0,
          "score_down": 0.0,
          "signed_contribution": 1.0,
          "abs_contribution": 1.0,
          "configured_weight": null,
          "reason": null
        },
        "D5": {
          "status": "active",
          "score_up": 0.675,
          "score_down": 0.0,
          "signed_contribution": 0.675,
          "abs_contribution": 0.675,
          "configured_weight": null,
          "reason": null
        },
        "D6": {
          "status": "active",
          "score_up": 1.0499999999999998,
          "score_down": 0.0,
          "signed_contribution": 1.0499999999999998,
          "abs_contribution": 1.0499999999999998,
          "configured_weight": null,
          "reason": null
        },
        "D7": {
          "status": "active",
          "score_up": 0.6000000000000001,
          "score_down": 0.0,
          "signed_contribution": 0.6000000000000001,
          "abs_contribution": 0.6000000000000001,
          "configured_weight": null,
          "reason": null
        },
        "D8": {
          "status": "active",
          "score_up": 1.105,
          "score_down": 0.0,
          "signed_contribution": 1.105,
          "abs_contribution": 1.105,
          "configured_weight": null,
          "reason": null
        }
      }
    },
    {
      "market_id": "btc-updown-5m-1780371000",
      "open_time": "2026-06-02T11:32:39.956635196+08:00",
      "entry_price": 0.6,
      "direction": "UP",
      "actual_result": "UNKNOWN",
      "success": false,
      "pnl": -3.0,
      "decision_timestamp": "2026-06-02T03:32:30.273964716Z",
      "d6_risk_level": "low",
      "d6_distance_shrinking": true,
      "d7_state": "active",
      "score_gap": 7.452164264584733,
      "confidence": 0.7452164264584733,
      "reject_reason": "",
      "final_block_reason": null,
      "factors": {
        "D1": {
          "status": "active",
          "score_up": 1.097164264584732,
          "score_down": 0.0,
          "signed_contribution": 1.097164264584732,
          "abs_contribution": 1.097164264584732,
          "configured_weight": null,
          "reason": null
        },
        "D2": {
          "status": "active",
          "score_up": 1.4,
          "score_down": 0.0,
          "signed_contribution": 1.4,
          "abs_contribution": 1.4,
          "configured_weight": null,
          "reason": null
        },
        "D3": {
          "status": "active",
          "score_up": 1.2,
          "score_down": 0.0,
          "signed_contribution": 1.2,
          "abs_contribution": 1.2,
          "configured_weight": null,
          "reason": null
        },
        "D4": {
          "status": "active",
          "score_up": 1.0,
          "score_down": 0.0,
          "signed_contribution": 1.0,
          "abs_contribution": 1.0,
          "configured_weight": null,
          "reason": null
        },
        "D5": {
          "status": "neutral",
          "score_up": 0.0,
          "score_down": 0.0,
          "signed_contribution": 0.0,
          "abs_contribution": 0.0,
          "configured_weight": null,
          "reason": null
        },
        "D6": {
          "status": "active",
          "score_up": 1.0499999999999998,
          "score_down": 0.0,
          "signed_contribution": 1.0499999999999998,
          "abs_contribution": 1.0499999999999998,
          "configured_weight": null,
          "reason": null
        },
        "D7": {
          "status": "active",
          "score_up": 0.6000000000000001,
          "score_down": 0.0,
          "signed_contribution": 0.6000000000000001,
          "abs_contribution": 0.6000000000000001,
          "configured_weight": null,
          "reason": null
        },
        "D8": {
          "status": "active",
          "score_up": 1.105,
          "score_down": 0.0,
          "signed_contribution": 1.105,
          "abs_contribution": 1.105,
          "configured_weight": null,
          "reason": null
        }
      }
    },
    {
      "market_id": "btc-updown-5m-1780371900",
      "open_time": "2026-06-02T11:48:16.222238885+08:00",
      "entry_price": 0.26,
      "direction": "UP",
      "actual_result": "UNKNOWN",
      "success": false,
      "pnl": -1.3,
      "decision_timestamp": "2026-06-02T03:48:05.487960234Z",
      "d6_risk_level": "low",
      "d6_distance_shrinking": false,
      "d7_state": "active",
      "score_gap": 8.355,
      "confidence": 0.8355,
      "reject_reason": "",
      "final_block_reason": null,
      "factors": {
        "D1": {
          "status": "active",
          "score_up": 2.0,
          "score_down": 0.0,
          "signed_contribution": 2.0,
          "abs_contribution": 2.0,
          "configured_weight": null,
          "reason": null
        },
        "D2": {
          "status": "active",
          "score_up": 1.4,
          "score_down": 0.0,
          "signed_contribution": 1.4,
          "abs_contribution": 1.4,
          "configured_weight": null,
          "reason": null
        },
        "D3": {
          "status": "active",
          "score_up": 1.2,
          "score_down": 0.0,
          "signed_contribution": 1.2,
          "abs_contribution": 1.2,
          "configured_weight": null,
          "reason": null
        },
        "D4": {
          "status": "active",
          "score_up": 1.0,
          "score_down": 0.0,
          "signed_contribution": 1.0,
          "abs_contribution": 1.0,
          "configured_weight": null,
          "reason": null
        },
        "D5": {
          "status": "neutral",
          "score_up": 0.0,
          "score_down": 0.0,
          "signed_contribution": 0.0,
          "abs_contribution": 0.0,
          "configured_weight": null,
          "reason": null
        },
        "D6": {
          "status": "active",
          "score_up": 1.0499999999999998,
          "score_down": 0.0,
          "signed_contribution": 1.0499999999999998,
          "abs_contribution": 1.0499999999999998,
          "configured_weight": null,
          "reason": null
        },
        "D7": {
          "status": "active",
          "score_up": 0.6000000000000001,
          "score_down": 0.0,
          "signed_contribution": 0.6000000000000001,
          "abs_contribution": 0.6000000000000001,
          "configured_weight": null,
          "reason": null
        },
        "D8": {
          "status": "active",
          "score_up": 1.105,
          "score_down": 0.0,
          "signed_contribution": 1.105,
          "abs_contribution": 1.105,
          "configured_weight": null,
          "reason": null
        }
      }
    },
    {
      "market_id": "btc-updown-5m-1780382400",
      "open_time": "2026-06-02T14:42:40.645838538+08:00",
      "entry_price": 0.6,
      "direction": "UP",
      "actual_result": "UNKNOWN",
      "success": false,
      "pnl": -3.0,
      "decision_timestamp": "2026-06-02T06:42:30.274172746Z",
      "d6_risk_level": "low",
      "d6_distance_shrinking": false,
      "d7_state": "active",
      "score_gap": 6.786738035574764,
      "confidence": 0.6786738035574764,
      "reject_reason": "",
      "final_block_reason": null,
      "factors": {
        "D1": {
          "status": "active",
          "score_up": 0.7527377572651672,
          "score_down": 0.0,
          "signed_contribution": 0.7527377572651672,
          "abs_contribution": 0.7527377572651672,
          "configured_weight": null,
          "reason": null
        },
        "D2": {
          "status": "active",
          "score_up": 1.4,
          "score_down": 0.0,
          "signed_contribution": 1.4,
          "abs_contribution": 1.4,
          "configured_weight": null,
          "reason": null
        },
        "D3": {
          "status": "active",
          "score_up": 1.1123285462086276,
          "score_down": 0.0,
          "signed_contribution": 1.1123285462086276,
          "abs_contribution": 1.1123285462086276,
          "configured_weight": null,
          "reason": null
        },
        "D4": {
          "status": "active",
          "score_up": 0.7666717321009687,
          "score_down": 0.0,
          "signed_contribution": 0.7666717321009687,
          "abs_contribution": 0.7666717321009687,
          "configured_weight": null,
          "reason": null
        },
        "D5": {
          "status": "neutral",
          "score_up": 0.0,
          "score_down": 0.0,
          "signed_contribution": 0.0,
          "abs_contribution": 0.0,
          "configured_weight": null,
          "reason": null
        },
        "D6": {
          "status": "active",
          "score_up": 1.0499999999999998,
          "score_down": 0.0,
          "signed_contribution": 1.0499999999999998,
          "abs_contribution": 1.0499999999999998,
          "configured_weight": null,
          "reason": null
        },
        "D7": {
          "status": "active",
          "score_up": 0.6000000000000001,
          "score_down": 0.0,
          "signed_contribution": 0.6000000000000001,
          "abs_contribution": 0.6000000000000001,
          "configured_weight": null,
          "reason": null
        },
        "D8": {
          "status": "active",
          "score_up": 1.105,
          "score_down": 0.0,
          "signed_contribution": 1.105,
          "abs_contribution": 1.105,
          "configured_weight": null,
          "reason": null
        }
      }
    }
  ]
}
